LICENSE
README.md
setup.py
c99api/__init__.py
c99api/api_handler.py
c99api/methods.py
c99api.egg-info/PKG-INFO
c99api.egg-info/SOURCES.txt
c99api.egg-info/dependency_links.txt
c99api.egg-info/requires.txt
c99api.egg-info/top_level.txt