Metadata-Version: 2.1
Name: c99api
Version: 1.0
Summary: A Python wrapper and handler for the c99.nl API
Home-page: https://github.com/Haste171/c99-api
Author: David Peterson
Author-email: dapanon@proton.me
License: MIT
Classifier: Development Status :: 3 - Alpha
Classifier: Intended Audience :: Developers
Classifier: License :: OSI Approved :: MIT License
Classifier: Programming Language :: Python :: 3
Classifier: Programming Language :: Python :: 3.6
Classifier: Programming Language :: Python :: 3.7
Classifier: Programming Language :: Python :: 3.8
Classifier: Programming Language :: Python :: 3.9
Classifier: Programming Language :: Python :: 3.10
License-File: LICENSE
